AUTHORS
INSTALL
LICENSE
MANIFEST.in
NOTICE
README.rst
requirements.txt
setup.cfg
setup.py
docs/Makefile
docs/conf.py
docs/configuration.rst
docs/faq.rst
docs/index.rst
docs/installation.rst
docs/introduction.rst
docs/make.bat
docs/usage.rst
src/django_taggit_autocomplete_modified.egg-info/PKG-INFO
src/django_taggit_autocomplete_modified.egg-info/SOURCES.txt
src/django_taggit_autocomplete_modified.egg-info/dependency_links.txt
src/django_taggit_autocomplete_modified.egg-info/not-zip-safe
src/django_taggit_autocomplete_modified.egg-info/top_level.txt
src/taggit_autocomplete_modified/__init__.py
src/taggit_autocomplete_modified/managers.py
src/taggit_autocomplete_modified/models.py
src/taggit_autocomplete_modified/settings.py
src/taggit_autocomplete_modified/tests.py
src/taggit_autocomplete_modified/urls.py
src/taggit_autocomplete_modified/views.py
src/taggit_autocomplete_modified/widgets.py
src/taggit_autocomplete_modified/static/taggit_autocomplete_modified/autocomplete.js
src/taggit_autocomplete_modified/static/taggit_autocomplete_modified/indicator.gif
src/taggit_autocomplete_modified/static/taggit_autocomplete_modified/jquery.autocomplete.css
src/taggit_autocomplete_modified/static/taggit_autocomplete_modified/jquery.autocomplete.js
src/taggit_autocomplete_modified/static/taggit_autocomplete_modified/jquery.min.js