Metadata-Version: 1.1
Name: django-taggit-autocomplete-modified
Version: 0.1.0b6
Summary: django-taggit-autocomplete-modified provides autocomplete functionality to the tags form field of django-taggit.
Home-page: http://www.codetrax.org/projects/django-taggit-autocomplete-modified
Author: George Notaras
Author-email: gnot [at] g-loaded.eu
License: Apache License version 2
Download-URL: https://source.codetrax.org/hgroot/django-taggit-autocomplete-modified
Platform: any
Classifier: Development Status :: 4 - Beta
Classifier: Environment :: Web Environment
Classifier: Framework :: Django
Classifier: Intended Audience :: Developers
Classifier: License :: OSI Approved :: Apache Software License
Classifier: Natural Language :: English
Classifier: Operating System :: OS Independent
Classifier: Programming Language :: Python
Classifier: Topic :: Internet :: WWW/HTTP :: Dynamic Content
Classifier: Topic :: Software Development :: Libraries :: Application Frameworks
Classifier: Topic :: Software Development :: Libraries :: Python Modules
